purerouter/__init__.py
purerouter/client.py
purerouter/errors.py
purerouter/types.py
purerouter/resources/deployments.py
purerouter/resources/router.py
purerouter-0.1.12.dist-info/METADATA
purerouter-0.1.12.dist-info/WHEEL
purerouter-0.1.12.dist-info/top_level.txt
purerouter-0.1.12.dist-info/RECORD
