Metadata-Version: 2.4
Name: purerouter
Version: 0.1.12
Summary: Python SDK for PureAI Router (sync + async)
Author: PureAI
Project-URL: Homepage, https://example.com
Requires-Python: >=3.9
Requires-Dist: httpx>=0.27
Requires-Dist: anyio>=4.0
Requires-Dist: typing-extensions>=4.9
